rkn/__init__.py
rkn/check_rkn.py
rkn-0.1.3.dist-info/METADATA
rkn-0.1.3.dist-info/RECORD
rkn-0.1.3.dist-info/WHEEL
rkn-0.1.3.dist-info/top_level.txt
