Metadata-Version: 2.1
Name: rkn
Version: 0.1.3
Summary: Check domain/ip address in http://blocklist.rkn.gov.ru database
Home-page: https://bitbucket.org/pi11/rkncheck/
Author: pi11
Author-email: co@defun.co
License: MIT
Platform: UNKNOWN
Requires-Dist: requests
Requires-Dist: antigate
Requires-Dist: pyquery
